bfxtelegram/__init__.py
bfxtelegram/__main__.py
bfxtelegram/bfxwss.py
bfxtelegram/btfxbot.py
bfxtelegram/tgraph.py
bfxtelegram/utils.py
tests/__init__.py
tests/conftest.py
tests/test_tgraph.py
tests/test_utils.py
bfxtelegram-1.1.0.dist-info/LICENSE
bfxtelegram-1.1.0.dist-info/METADATA
bfxtelegram-1.1.0.dist-info/WHEEL
bfxtelegram-1.1.0.dist-info/entry_points.txt
bfxtelegram-1.1.0.dist-info/top_level.txt
bfxtelegram-1.1.0.dist-info/zip-safe
bfxtelegram-1.1.0.dist-info/RECORD
