Metadata-Version: 2.1
Name: bfxtelegram
Version: 1.1.0
Summary: Control Bitfinex account with a Telegram bot
Home-page: https://github.com/dantimofte/bfxtelegram
Author: Dan Timofte
Author-email: dantimofte@pm.me
License: MIT
Keywords: bitcoin,btc,iota,telegram,bitfinex
Platform: UNKNOWN
Requires-Dist: wheel
Requires-Dist: pandas
Requires-Dist: pillow
Requires-Dist: selenium
Requires-Dist: bokeh
Requires-Dist: python-telegram-bot
Requires-Dist: bitfinex-v2 (==1.0.0)
